LICENSE
README.md
tinybridge/__init__.py
tinybridge/aiobridge.py
tinybridge-0.1.4.dist-info/METADATA
tinybridge-0.1.4.dist-info/WHEEL
tinybridge-0.1.4.dist-info/licenses/LICENSE
tinybridge-0.1.4.dist-info/RECORD
