Metadata-Version: 2.4
Name: tinybridge
Version: 0.1.4
Summary: TinyDB bridge implementation for asyncio-based applications
Project-URL: Homepage, https://github.com/mrprfrm/tinybridge
Author-email: Anton Petrov <mrprfrm@gmail.com>
License-Expression: MIT
License-File: LICENSE
Classifier: Intended Audience :: Developers
Classifier: Programming Language :: Python :: 3
Classifier: Topic :: Database
Classifier: Typing :: Typed
Requires-Python: >=3.9
Requires-Dist: result
Requires-Dist: tinydb
